aiida_qeq/__init__.py
aiida_qeq/calculations/__init__.py
aiida_qeq/calculations/eqeq.py
aiida_qeq/calculations/qeq.py
aiida_qeq/data/__init__.py
aiida_qeq/data/data_cli.py
aiida_qeq/data/eqeq.py
aiida_qeq/data/qeq.py
aiida_qeq/parsers/__init__.py
aiida_qeq/parsers/eqeq.py
aiida_qeq/parsers/qeq.py
aiida_qeq/tests/__init__.py
aiida_qeq/tests/test_calculations.py
aiida_qeq/tests/test_data.py
aiida_qeq/tests/test_parsers.py
aiida_qeq-0.1.0.dist-info/LICENSE
aiida_qeq-0.1.0.dist-info/METADATA
aiida_qeq-0.1.0.dist-info/WHEEL
aiida_qeq-0.1.0.dist-info/entry_points.txt
aiida_qeq-0.1.0.dist-info/top_level.txt
aiida_qeq-0.1.0.dist-info/RECORD
