Metadata-Version: 2.1
Name: aiida-qeq
Version: 0.1.0
Summary: AiiDA plugin for computing electronic charges on atoms using equilibration-type models (QEq, EQEq, ...).
Home-page: https://github.com/ltalirz/aiida-qeq
Author: Leopold Talirz, Daniele Ongari
Author-email: leopold.talirz@gmail.com
License: MIT
Platform: UNKNOWN
Classifier: Programming Language :: Python
Requires-Dist: aiida-core (<1.0.0,>=0.12.2)
Requires-Dist: six
Provides-Extra: docs
Requires-Dist: sphinx ; extra == 'docs'
Provides-Extra: pre-commit
Requires-Dist: pre-commit (==1.11.0) ; extra == 'pre-commit'
Requires-Dist: yapf (==0.24.0) ; extra == 'pre-commit'
Requires-Dist: prospector (==0.12.11) ; extra == 'pre-commit'
Requires-Dist: pylint (==1.9.3) ; extra == 'pre-commit'
Provides-Extra: testing
Requires-Dist: mock (==2.0.0) ; extra == 'testing'
Requires-Dist: pgtest (==1.1.0) ; extra == 'testing'
Requires-Dist: sqlalchemy-diff (==0.1.3) ; extra == 'testing'
Requires-Dist: wheel (>=0.31) ; extra == 'testing'
Requires-Dist: coverage ; extra == 'testing'
